{
  "result": {
    "enterprises.dating.boo": {
      "subscription packages": {
        "rank": {
          "value": null,
          "date": "2026-04-10",
          "effective_value": 501,
          "fetch_performed": true
        },
        "relevancy": {
          "value": 26,
          "date": "2026-04-10",
          "effective_value": 26
        },
        "kei": {
          "value": 22,
          "date": "2026-04-10",
          "effective_value": 22
        },
        "chance": {
          "value": 73,
          "date": "2026-04-10",
          "effective_value": 73
        }
      },
      "non subscription": {
        "rank": {
          "value": null,
          "date": "2026-04-10",
          "effective_value": 501,
          "fetch_performed": true
        },
        "relevancy": {
          "value": 34,
          "date": "2026-04-10",
          "effective_value": 34
        },
        "kei": {
          "value": 22,
          "date": "2026-04-10",
          "effective_value": 22
        },
        "chance": {
          "value": 73,
          "date": "2026-04-10",
          "effective_value": 73
        }
      },
      "subscription single": {
        "rank": {
          "value": null,
          "date": "2026-04-10",
          "effective_value": 501,
          "fetch_performed": true
        },
        "relevancy": {
          "value": 91,
          "date": "2026-04-10",
          "effective_value": 91
        },
        "kei": {
          "value": 22,
          "date": "2026-04-10",
          "effective_value": 22
        },
        "chance": {
          "value": 73,
          "date": "2026-04-10",
          "effective_value": 73
        }
      },
      "single multi": {
        "rank": {
          "value": null,
          "date": "2026-04-10",
          "effective_value": 501,
          "fetch_performed": true
        },
        "relevancy": {
          "value": 27,
          "date": "2026-04-10",
          "effective_value": 27
        },
        "kei": {
          "value": 11,
          "date": "2026-04-10",
          "effective_value": 11
        },
        "chance": {
          "value": 36,
          "date": "2026-04-10",
          "effective_value": 36
        }
      },
      "multi use": {
        "rank": {
          "value": null,
          "date": "2026-04-10",
          "effective_value": 501,
          "fetch_performed": true
        },
        "relevancy": {
          "value": 18,
          "date": "2026-04-10",
          "effective_value": 18
        },
        "kei": {
          "value": 22,
          "date": "2026-04-10",
          "effective_value": 22
        },
        "chance": {
          "value": 73,
          "date": "2026-04-10",
          "effective_value": 73
        }
      }
    },
    "com.getpure.pure": {
      "subscription packages": {
        "rank": {
          "value": null,
          "date": "2026-04-10",
          "effective_value": 501,
          "fetch_performed": true
        },
        "relevancy": {
          "value": 32,
          "date": "2026-04-10",
          "effective_value": 32
        },
        "kei": {
          "value": 22,
          "date": "2026-04-10",
          "effective_value": 22
        },
        "chance": {
          "value": 73,
          "date": "2026-04-10",
          "effective_value": 73
        }
      },
      "non subscription": {
        "rank": {
          "value": null,
          "date": "2026-04-10",
          "effective_value": 501,
          "fetch_performed": true
        },
        "relevancy": {
          "value": 38,
          "date": "2026-04-10",
          "effective_value": 38
        },
        "kei": {
          "value": 22,
          "date": "2026-04-10",
          "effective_value": 22
        },
        "chance": {
          "value": 73,
          "date": "2026-04-10",
          "effective_value": 73
        }
      },
      "subscription single": {
        "rank": {
          "value": null,
          "date": "2026-04-10",
          "effective_value": 501,
          "fetch_performed": true
        },
        "relevancy": {
          "value": 89,
          "date": "2026-04-10",
          "effective_value": 89
        },
        "kei": {
          "value": 22,
          "date": "2026-04-10",
          "effective_value": 22
        },
        "chance": {
          "value": 73,
          "date": "2026-04-10",
          "effective_value": 73
        }
      },
      "single multi": {
        "rank": {
          "value": null,
          "date": "2026-04-10",
          "effective_value": 501,
          "fetch_performed": true
        },
        "relevancy": {
          "value": 38,
          "date": "2026-04-10",
          "effective_value": 38
        },
        "kei": {
          "value": 11,
          "date": "2026-04-10",
          "effective_value": 11
        },
        "chance": {
          "value": 36,
          "date": "2026-04-10",
          "effective_value": 36
        }
      },
      "multi use": {
        "rank": {
          "value": null,
          "date": "2026-04-10",
          "effective_value": 501,
          "fetch_performed": true
        },
        "relevancy": {
          "value": 20,
          "date": "2026-04-10",
          "effective_value": 20
        },
        "kei": {
          "value": 22,
          "date": "2026-04-10",
          "effective_value": 22
        },
        "chance": {
          "value": 72,
          "date": "2026-04-10",
          "effective_value": 72
        }
      }
    },
    "com.nearme.wolf": {
      "subscription packages": {
        "rank": {
          "value": null,
          "date": "2026-04-10",
          "effective_value": 501,
          "fetch_performed": true
        },
        "relevancy": {
          "value": 40,
          "date": "2026-04-10",
          "effective_value": 40
        },
        "kei": {
          "value": 22,
          "date": "2026-04-10",
          "effective_value": 22
        },
        "chance": {
          "value": 73,
          "date": "2026-04-10",
          "effective_value": 73
        }
      },
      "non subscription": {
        "rank": {
          "value": null,
          "date": "2026-04-10",
          "effective_value": 501,
          "fetch_performed": true
        },
        "relevancy": {
          "value": 30,
          "date": "2026-04-10",
          "effective_value": 30
        },
        "kei": {
          "value": 22,
          "date": "2026-04-10",
          "effective_value": 22
        },
        "chance": {
          "value": 73,
          "date": "2026-04-10",
          "effective_value": 73
        }
      },
      "subscription single": {
        "rank": {
          "value": null,
          "date": "2026-04-10",
          "effective_value": 501,
          "fetch_performed": true
        },
        "relevancy": {
          "value": 74,
          "date": "2026-04-10",
          "effective_value": 74
        },
        "kei": {
          "value": 22,
          "date": "2026-04-10",
          "effective_value": 22
        },
        "chance": {
          "value": 73,
          "date": "2026-04-10",
          "effective_value": 73
        }
      },
      "single multi": {
        "rank": {
          "value": null,
          "date": "2026-04-10",
          "effective_value": 501,
          "fetch_performed": true
        },
        "relevancy": {
          "value": 28,
          "date": "2026-04-10",
          "effective_value": 28
        },
        "kei": {
          "value": 5,
          "date": "2026-04-10",
          "effective_value": 5
        },
        "chance": {
          "value": 15,
          "date": "2026-04-10",
          "effective_value": 15
        }
      },
      "multi use": {
        "rank": {
          "value": null,
          "date": "2026-04-10",
          "effective_value": 501,
          "fetch_performed": true
        },
        "relevancy": {
          "value": 6,
          "date": "2026-04-10",
          "effective_value": 6
        },
        "kei": {
          "value": 14,
          "date": "2026-04-10",
          "effective_value": 14
        },
        "chance": {
          "value": 46,
          "date": "2026-04-10",
          "effective_value": 46
        }
      }
    },
    "com.pof.android": {
      "subscription packages": {
        "rank": {
          "value": null,
          "date": "2026-04-10",
          "effective_value": 501,
          "fetch_performed": true
        },
        "relevancy": {
          "value": 36,
          "date": "2026-04-10",
          "effective_value": 36
        },
        "kei": {
          "value": 22,
          "date": "2026-04-10",
          "effective_value": 22
        },
        "chance": {
          "value": 73,
          "date": "2026-04-10",
          "effective_value": 73
        }
      },
      "non subscription": {
        "rank": {
          "value": null,
          "date": "2026-04-10",
          "effective_value": 501,
          "fetch_performed": true
        },
        "relevancy": {
          "value": 41,
          "date": "2026-04-10",
          "effective_value": 41
        },
        "kei": {
          "value": 22,
          "date": "2026-04-10",
          "effective_value": 22
        },
        "chance": {
          "value": 73,
          "date": "2026-04-10",
          "effective_value": 73
        }
      },
      "subscription single": {
        "rank": {
          "value": 47,
          "date": "2026-04-10",
          "effective_value": 47,
          "fetch_performed": true
        },
        "relevancy": {
          "value": 91,
          "date": "2026-04-10",
          "effective_value": 91
        },
        "kei": {
          "value": 22,
          "date": "2026-04-10",
          "effective_value": 22
        },
        "chance": {
          "value": 73,
          "date": "2026-04-10",
          "effective_value": 73
        }
      },
      "single multi": {
        "rank": {
          "value": null,
          "date": "2026-04-10",
          "effective_value": 501,
          "fetch_performed": true
        },
        "relevancy": {
          "value": 31,
          "date": "2026-04-10",
          "effective_value": 31
        },
        "kei": {
          "value": 7,
          "date": "2026-04-10",
          "effective_value": 7
        },
        "chance": {
          "value": 24,
          "date": "2026-04-10",
          "effective_value": 24
        }
      },
      "multi use": {
        "rank": {
          "value": null,
          "date": "2026-04-10",
          "effective_value": 501,
          "fetch_performed": true
        },
        "relevancy": {
          "value": 21,
          "date": "2026-04-10",
          "effective_value": 21
        },
        "kei": {
          "value": 18,
          "date": "2026-04-10",
          "effective_value": 18
        },
        "chance": {
          "value": 60,
          "date": "2026-04-10",
          "effective_value": 60
        }
      }
    }
  },
  "metadata": {
    "request": {
      "path": "/api/public/store/apps/keywords-rankings/current.json",
      "params": {
        "device": "android",
        "country": "us",
        "language": "us",
        "apps": [
          "enterprises.dating.boo",
          "com.getpure.pure",
          "com.nearme.wolf",
          "com.pof.android"
        ],
        "metrics": [
          "rank",
          "relevancy",
          "kei",
          "chance"
        ],
        "keywords": [
          "subscription packages",
          "non subscription",
          "subscription single",
          "single multi",
          "multi use"
        ]
      },
      "cost": 801,
      "max_credit_cost": 801,
      "status": 200
    },
    "response": null
  }
}