{
  "result": {
    "601174087": {
      "online dating": {
        "rank": {
          "value": null,
          "date": "2026-04-10",
          "effective_value": 501,
          "fetch_performed": true
        },
        "relevancy": {
          "value": 91,
          "date": "2026-04-10",
          "effective_value": 91
        },
        "kei": {
          "value": 8,
          "date": "2026-04-10",
          "effective_value": 8
        },
        "chance": {
          "value": 28,
          "date": "2026-04-10",
          "effective_value": 28
        }
      },
      "chat": {
        "rank": {
          "value": 113,
          "date": "2026-04-10",
          "effective_value": 113,
          "fetch_performed": true
        },
        "relevancy": {
          "value": 80,
          "date": "2026-04-10",
          "effective_value": 80
        },
        "kei": {
          "value": 46,
          "date": "2026-04-10",
          "effective_value": 46
        },
        "chance": {
          "value": 26,
          "date": "2026-04-10",
          "effective_value": 26
        }
      },
      "video calling": {
        "rank": {
          "value": null,
          "date": "2026-04-10",
          "effective_value": 501,
          "fetch_performed": true
        },
        "relevancy": {
          "value": 73,
          "date": "2026-04-10",
          "effective_value": 73
        },
        "kei": {
          "value": 11,
          "date": "2026-04-10",
          "effective_value": 11
        },
        "chance": {
          "value": 36,
          "date": "2026-04-10",
          "effective_value": 36
        }
      },
      "verified profiles": {
        "rank": {
          "value": null,
          "date": "2026-04-10",
          "effective_value": 501,
          "fetch_performed": true
        },
        "relevancy": {
          "value": 46,
          "date": "2026-04-10",
          "effective_value": 46
        },
        "kei": {
          "value": 15,
          "date": "2026-04-10",
          "effective_value": 15
        },
        "chance": {
          "value": 73,
          "date": "2026-04-10",
          "effective_value": 73
        }
      },
      "safe space": {
        "rank": {
          "value": null,
          "date": "2026-04-10",
          "effective_value": 501,
          "fetch_performed": true
        },
        "relevancy": {
          "value": 36,
          "date": "2026-04-10",
          "effective_value": 36
        },
        "kei": {
          "value": 22,
          "date": "2026-04-10",
          "effective_value": 22
        },
        "chance": {
          "value": 73,
          "date": "2026-04-10",
          "effective_value": 73
        }
      }
    },
    "1250946975": {
      "online dating": {
        "rank": {
          "value": 18,
          "date": "2026-04-10",
          "effective_value": 18,
          "fetch_performed": true
        },
        "relevancy": {
          "value": 89,
          "date": "2026-04-10",
          "effective_value": 89
        },
        "kei": {
          "value": 16,
          "date": "2026-04-10",
          "effective_value": 16
        },
        "chance": {
          "value": 54,
          "date": "2026-04-10",
          "effective_value": 54
        }
      },
      "chat": {
        "rank": {
          "value": 72,
          "date": "2026-04-10",
          "effective_value": 72,
          "fetch_performed": true
        },
        "relevancy": {
          "value": 82,
          "date": "2026-04-10",
          "effective_value": 82
        },
        "kei": {
          "value": 72,
          "date": "2026-04-10",
          "effective_value": 72
        },
        "chance": {
          "value": 52,
          "date": "2026-04-10",
          "effective_value": 52
        }
      },
      "video calling": {
        "rank": {
          "value": null,
          "date": "2026-04-10",
          "effective_value": 501,
          "fetch_performed": true
        },
        "relevancy": {
          "value": 77,
          "date": "2026-04-10",
          "effective_value": 77
        },
        "kei": {
          "value": 19,
          "date": "2026-04-10",
          "effective_value": 19
        },
        "chance": {
          "value": 63,
          "date": "2026-04-10",
          "effective_value": 63
        }
      },
      "verified profiles": {
        "rank": {
          "value": null,
          "date": "2026-04-10",
          "effective_value": 501,
          "fetch_performed": true
        },
        "relevancy": {
          "value": 50,
          "date": "2026-04-10",
          "effective_value": 50
        },
        "kei": {
          "value": 15,
          "date": "2026-04-10",
          "effective_value": 15
        },
        "chance": {
          "value": 73,
          "date": "2026-04-10",
          "effective_value": 73
        }
      },
      "safe space": {
        "rank": {
          "value": null,
          "date": "2026-04-10",
          "effective_value": 501,
          "fetch_performed": true
        },
        "relevancy": {
          "value": 35,
          "date": "2026-04-10",
          "effective_value": 35
        },
        "kei": {
          "value": 22,
          "date": "2026-04-10",
          "effective_value": 22
        },
        "chance": {
          "value": 73,
          "date": "2026-04-10",
          "effective_value": 73
        }
      }
    },
    "690661663": {
      "online dating": {
        "rank": {
          "value": 6,
          "date": "2026-04-10",
          "effective_value": 6,
          "fetch_performed": true
        },
        "relevancy": {
          "value": 83,
          "date": "2026-04-10",
          "effective_value": 83
        },
        "kei": {
          "value": 25,
          "date": "2026-04-10",
          "effective_value": 25
        },
        "chance": {
          "value": 82,
          "date": "2026-04-10",
          "effective_value": 82
        }
      },
      "chat": {
        "rank": {
          "value": 59,
          "date": "2026-04-10",
          "effective_value": 59,
          "fetch_performed": true
        },
        "relevancy": {
          "value": 74,
          "date": "2026-04-10",
          "effective_value": 74
        },
        "kei": {
          "value": 64,
          "date": "2026-04-10",
          "effective_value": 64
        },
        "chance": {
          "value": 44,
          "date": "2026-04-10",
          "effective_value": 44
        }
      },
      "video calling": {
        "rank": {
          "value": null,
          "date": "2026-04-10",
          "effective_value": 501,
          "fetch_performed": true
        },
        "relevancy": {
          "value": 69,
          "date": "2026-04-10",
          "effective_value": 69
        },
        "kei": {
          "value": 17,
          "date": "2026-04-10",
          "effective_value": 17
        },
        "chance": {
          "value": 55,
          "date": "2026-04-10",
          "effective_value": 55
        }
      },
      "verified profiles": {
        "rank": {
          "value": null,
          "date": "2026-04-10",
          "effective_value": 501,
          "fetch_performed": true
        },
        "relevancy": {
          "value": 57,
          "date": "2026-04-10",
          "effective_value": 57
        },
        "kei": {
          "value": 15,
          "date": "2026-04-10",
          "effective_value": 15
        },
        "chance": {
          "value": 73,
          "date": "2026-04-10",
          "effective_value": 73
        }
      },
      "safe space": {
        "rank": {
          "value": null,
          "date": "2026-04-10",
          "effective_value": 501,
          "fetch_performed": true
        },
        "relevancy": {
          "value": 51,
          "date": "2026-04-10",
          "effective_value": 51
        },
        "kei": {
          "value": 22,
          "date": "2026-04-10",
          "effective_value": 22
        },
        "chance": {
          "value": 73,
          "date": "2026-04-10",
          "effective_value": 73
        }
      }
    },
    "1265035248": {
      "online dating": {
        "rank": {
          "value": 33,
          "date": "2026-04-10",
          "effective_value": 33,
          "fetch_performed": true
        },
        "relevancy": {
          "value": 92,
          "date": "2026-04-10",
          "effective_value": 92
        },
        "kei": {
          "value": 1,
          "date": "2026-04-10",
          "effective_value": 1
        },
        "chance": {
          "value": 3,
          "date": "2026-04-10",
          "effective_value": 3
        }
      },
      "chat": {
        "rank": {
          "value": 167,
          "date": "2026-04-10",
          "effective_value": 167,
          "fetch_performed": true
        },
        "relevancy": {
          "value": 82,
          "date": "2026-04-10",
          "effective_value": 82
        },
        "kei": {
          "value": 23,
          "date": "2026-04-10",
          "effective_value": 23
        },
        "chance": {
          "value": 3,
          "date": "2026-04-10",
          "effective_value": 3
        }
      },
      "video calling": {
        "rank": {
          "value": null,
          "date": "2026-04-10",
          "effective_value": 501,
          "fetch_performed": true
        },
        "relevancy": {
          "value": 73,
          "date": "2026-04-10",
          "effective_value": 73
        },
        "kei": {
          "value": 2,
          "date": "2026-04-10",
          "effective_value": 2
        },
        "chance": {
          "value": 6,
          "date": "2026-04-10",
          "effective_value": 6
        }
      },
      "verified profiles": {
        "rank": {
          "value": null,
          "date": "2026-04-10",
          "effective_value": 501,
          "fetch_performed": true
        },
        "relevancy": {
          "value": 54,
          "date": "2026-04-10",
          "effective_value": 54
        },
        "kei": {
          "value": 10,
          "date": "2026-04-10",
          "effective_value": 10
        },
        "chance": {
          "value": 52,
          "date": "2026-04-10",
          "effective_value": 52
        }
      },
      "safe space": {
        "rank": {
          "value": null,
          "date": "2026-04-10",
          "effective_value": 501,
          "fetch_performed": true
        },
        "relevancy": {
          "value": 43,
          "date": "2026-04-10",
          "effective_value": 43
        },
        "kei": {
          "value": 17,
          "date": "2026-04-10",
          "effective_value": 17
        },
        "chance": {
          "value": 58,
          "date": "2026-04-10",
          "effective_value": 58
        }
      }
    }
  },
  "metadata": {
    "request": {
      "path": "/api/public/store/apps/keywords-rankings/current.json",
      "params": {
        "device": "iphone",
        "country": "us",
        "language": "us",
        "apps": [
          "601174087",
          "1250946975",
          "690661663",
          "1265035248"
        ],
        "metrics": [
          "rank",
          "relevancy",
          "kei",
          "chance"
        ],
        "keywords": [
          "online dating",
          "chat",
          "video calling",
          "verified profiles",
          "safe space"
        ]
      },
      "cost": 801,
      "max_credit_cost": 801,
      "status": 200
    },
    "response": null
  }
}